sensehi/__init__.py
sensehi/hello.py
sensehi/lib.py
sensehi/niimaskplot.py
sensehi-0.0.6.dist-info/LICENSE
sensehi-0.0.6.dist-info/METADATA
sensehi-0.0.6.dist-info/WHEEL
sensehi-0.0.6.dist-info/top_level.txt
sensehi-0.0.6.dist-info/RECORD
