Metadata-Version: 2.1
Name: sensehi
Version: 0.0.6
Summary: demo
Home-page: https://github.com/...
Author: yyx
Author-email: 954053501@qq.com
License: UNKNOWN
Platform: UNKNOWN
